CHANGES.rst
CONTRIBUTORS.rst
DEVELOP.rst
LICENSE.GPL
LICENSE.rst
MANIFEST.in
README.rst
setup.cfg
setup.py
docs/conf.py
docs/index.rst
src/collective/__init__.py
src/collective.resourcebooking.egg-info/PKG-INFO
src/collective.resourcebooking.egg-info/SOURCES.txt
src/collective.resourcebooking.egg-info/dependency_links.txt
src/collective.resourcebooking.egg-info/entry_points.txt
src/collective.resourcebooking.egg-info/namespace_packages.txt
src/collective.resourcebooking.egg-info/not-zip-safe
src/collective.resourcebooking.egg-info/requires.txt
src/collective.resourcebooking.egg-info/top_level.txt
src/collective/resourcebooking/__init__.py
src/collective/resourcebooking/configure.zcml
src/collective/resourcebooking/interfaces.py
src/collective/resourcebooking/permissions.zcml
src/collective/resourcebooking/setuphandlers.py
src/collective/resourcebooking/testing.py
src/collective/resourcebooking/browser/__init__.py
src/collective/resourcebooking/browser/configure.zcml
src/collective/resourcebooking/browser/overrides/.gitkeep
src/collective/resourcebooking/browser/static/.gitkeep
src/collective/resourcebooking/browser/static/resourcebooking.css
src/collective/resourcebooking/content/__init__.py
src/collective/resourcebooking/content/booking.py
src/collective/resourcebooking/content/bookings.py
src/collective/resourcebooking/content/resource.py
src/collective/resourcebooking/content/resource_booking.py
src/collective/resourcebooking/content/resources.py
src/collective/resourcebooking/forms/__init__.py
src/collective/resourcebooking/forms/booking_default_add_form.py
src/collective/resourcebooking/forms/booking_edit_form.py
src/collective/resourcebooking/forms/configure.zcml
src/collective/resourcebooking/indexers/__init__.py
src/collective/resourcebooking/indexers/configure.zcml
src/collective/resourcebooking/indexers/resource.py
src/collective/resourcebooking/indexers/resource.zcml
src/collective/resourcebooking/indexers/timeslot.py
src/collective/resourcebooking/indexers/timeslot.zcml
src/collective/resourcebooking/locales/README.rst
src/collective/resourcebooking/locales/__init__.py
src/collective/resourcebooking/locales/collective.resourcebooking.pot
src/collective/resourcebooking/locales/update.py
src/collective/resourcebooking/locales/update.sh
src/collective/resourcebooking/locales/de/LC_MESSAGES/collective.resourcebooking.po
