Metadata-Version: 2.1
Name: collective.resourcebooking
Version: 1.0b1
Summary: Allow users to book resources like rooms in Plone
Home-page: https://github.com/collective/collective.resourcebooking
Author: Maik Derstappen
Author-email: md@derico.de
License: GPL version 2
Project-URL: PyPI, https://pypi.org/project/collective.resourcebooking/
Project-URL: Source, https://github.com/collective/collective.resourcebooking
Project-URL: Tracker, https://github.com/collective/collective.resourcebooking/issues
Keywords: Python Plone CMS
Classifier: Environment :: Web Environment
Classifier: Framework :: Plone
Classifier: Framework :: Plone :: Addon
Classifier: Framework :: Plone :: 5.2
Classifier: Framework :: Plone :: 6.0
Classifier: Programming Language :: Python
Classifier: Programming Language :: Python :: 3.7
Classifier: Programming Language :: Python :: 3.8
Classifier: Programming Language :: Python :: 3.9
Classifier: Operating System :: OS Independent
Classifier: License :: OSI Approved :: GNU General Public License v2 (GPLv2)
Requires-Python: >=3.7
Provides-Extra: test
License-File: LICENSE.GPL
License-File: LICENSE.rst
